{
  "generatedAt": "2026-06-22T12:57:10.308Z",
  "cash": 1091844,
  "holdings": [
    {
      "id": "holding1",
      "symbol": "0050",
      "shares": 200,
      "avgCost": 96.6,
      "broker": "Mega",
      "account": "Default",
      "name": "元大台灣50",
      "market": "TWSE",
      "marketName": "上市",
      "yahooSymbol": "0050.TW",
      "sector": "ETF",
      "currentPrice": 111.15,
      "previousClose": 107.30000305175781,
      "change": 3.849996948242193,
      "changePercent": 3.5880678832647264,
      "eps": null,
      "pe": null,
      "forwardPe": null,
      "cost": 19320,
      "marketValue": 22230,
      "todayPnL": 769.9993896484386,
      "unrealizedPnL": 2910,
      "unrealizedPnLPct": 15.062111801242237,
      "weight": 0.8427078101159055,
      "dataStatus": "fundamentals_missing",
      "failedProviders": [
        "TPEX API: not TPEX",
        "Yahoo Finance: Yahoo fundamentals 0050 HTTP 401",
        "TradingView: TradingView 0050 HTTP 404",
        "WantGoo: WantGoo fundamentals 0050 HTTP 403"
      ],
      "source": "Yahoo Finance chart",
      "updatedAt": "2026-06-22T12:56:56.622Z"
    },
    {
      "id": "holding2",
      "symbol": "2301",
      "shares": 1,
      "avgCost": 174,
      "broker": "Mega",
      "account": "Default",
      "name": "光寶科",
      "market": "TWSE",
      "marketName": "上市",
      "yahooSymbol": "2301.TW",
      "sector": "電子",
      "currentPrice": 231.5,
      "previousClose": 210.5,
      "change": 21,
      "changePercent": 9.97624703087886,
      "eps": null,
      "pe": null,
      "forwardPe": null,
      "cost": 174,
      "marketValue": 231.5,
      "todayPnL": 21,
      "unrealizedPnL": 57.5,
      "unrealizedPnLPct": 33.04597701149425,
      "weight": 0.008775837068908329,
      "dataStatus": "fundamentals_missing",
      "failedProviders": [
        "TPEX API: not TPEX",
        "Yahoo Finance: Yahoo fundamentals 2301 HTTP 401",
        "WantGoo: WantGoo fundamentals 2301 HTTP 403"
      ],
      "source": "Yahoo Finance chart",
      "updatedAt": "2026-06-22T12:56:44.753Z"
    },
    {
      "id": "holding3",
      "symbol": "2316",
      "shares": 60,
      "avgCost": 133.83,
      "broker": "Mega",
      "account": "Default",
      "name": "楠梓電",
      "market": "TWSE",
      "marketName": "上市",
      "yahooSymbol": "2316.TW",
      "sector": "電子",
      "currentPrice": 226,
      "previousClose": 205.5,
      "change": 20.5,
      "changePercent": 9.975669099756692,
      "eps": null,
      "pe": null,
      "forwardPe": null,
      "cost": 8029.800000000001,
      "marketValue": 13560,
      "todayPnL": 1230,
      "unrealizedPnL": 5530.199999999999,
      "unrealizedPnLPct": 68.87095569005453,
      "weight": 0.5140403915956671,
      "dataStatus": "fundamentals_missing",
      "failedProviders": [
        "TPEX API: not TPEX",
        "Yahoo Finance: Yahoo fundamentals 2316 HTTP 401",
        "WantGoo: WantGoo fundamentals 2316 HTTP 403"
      ],
      "source": "Yahoo Finance chart",
      "updatedAt": "2026-06-22T12:56:44.789Z"
    },
    {
      "id": "holding4",
      "symbol": "2317",
      "shares": 400,
      "avgCost": 218.53,
      "broker": "Mega",
      "account": "Default",
      "name": "鴻海",
      "market": "TWSE",
      "marketName": "上市",
      "yahooSymbol": "2317.TW",
      "sector": "電子",
      "currentPrice": 268.5,
      "previousClose": 268.5,
      "change": 0,
      "changePercent": 0,
      "eps": null,
      "pe": null,
      "forwardPe": null,
      "cost": 87412,
      "marketValue": 107400,
      "todayPnL": 0,
      "unrealizedPnL": 19988,
      "unrealizedPnLPct": 22.86642566238045,
      "weight": 4.071381862638248,
      "dataStatus": "fundamentals_missing",
      "failedProviders": [
        "TPEX API: not TPEX",
        "Yahoo Finance: Yahoo fundamentals 2317 HTTP 401",
        "WantGoo: WantGoo fundamentals 2317 HTTP 403"
      ],
      "source": "Yahoo Finance chart",
      "updatedAt": "2026-06-22T12:56:44.882Z"
    },
    {
      "id": "holding5",
      "symbol": "2327",
      "shares": 160,
      "avgCost": 281.13,
      "broker": "Mega",
      "account": "Default",
      "name": "國巨*",
      "market": "TWSE",
      "marketName": "上市",
      "yahooSymbol": "2327.TW",
      "sector": "電子",
      "currentPrice": 1065,
      "previousClose": 1080,
      "change": -15,
      "changePercent": -1.3888888888888888,
      "eps": null,
      "pe": null,
      "forwardPe": null,
      "cost": 44980.8,
      "marketValue": 170400,
      "todayPnL": -2400,
      "unrealizedPnL": 125419.2,
      "unrealizedPnLPct": 278.8283000746985,
      "weight": 6.4596226200517455,
      "dataStatus": "fundamentals_missing",
      "failedProviders": [
        "TPEX API: not TPEX",
        "Yahoo Finance: Yahoo fundamentals 2327 HTTP 401",
        "WantGoo: WantGoo fundamentals 2327 HTTP 403"
      ],
      "source": "Yahoo Finance chart",
      "updatedAt": "2026-06-22T12:56:44.896Z"
    },
    {
      "id": "holding6",
      "symbol": "2330",
      "shares": 175,
      "avgCost": 1855,
      "broker": "Mega",
      "account": "Default",
      "name": "台積電",
      "market": "TWSE",
      "marketName": "上市",
      "yahooSymbol": "2330.TW",
      "sector": "電子",
      "currentPrice": 2510,
      "previousClose": 2410,
      "change": 100,
      "changePercent": 4.149377593360995,
      "eps": null,
      "pe": null,
      "forwardPe": null,
      "cost": 324625,
      "marketValue": 439250,
      "todayPnL": 17500,
      "unrealizedPnL": 114625,
      "unrealizedPnLPct": 35.309973045822105,
      "weight": 16.651345280855217,
      "dataStatus": "fundamentals_missing",
      "failedProviders": [
        "TPEX API: not TPEX",
        "Yahoo Finance: Yahoo fundamentals 2330 HTTP 401",
        "WantGoo: WantGoo fundamentals 2330 HTTP 403"
      ],
      "source": "Yahoo Finance chart",
      "updatedAt": "2026-06-22T12:56:44.879Z"
    },
    {
      "id": "holding7",
      "symbol": "2357",
      "shares": 25,
      "avgCost": 569,
      "broker": "Mega",
      "account": "Default",
      "name": "華碩",
      "market": "TWSE",
      "marketName": "上市",
      "yahooSymbol": "2357.TW",
      "sector": "電子",
      "currentPrice": 788,
      "previousClose": 789,
      "change": -1,
      "changePercent": -0.12674271229404308,
      "eps": null,
      "pe": null,
      "forwardPe": null,
      "cost": 14225,
      "marketValue": 19700,
      "todayPnL": -25,
      "unrealizedPnL": 5475,
      "unrealizedPnLPct": 38.488576449912124,
      "weight": 0.7467990939848556,
      "dataStatus": "fundamentals_missing",
      "failedProviders": [
        "TPEX API: not TPEX",
        "Yahoo Finance: Yahoo fundamentals 2357 HTTP 401",
        "WantGoo: WantGoo fundamentals 2357 HTTP 403"
      ],
      "source": "Yahoo Finance chart",
      "updatedAt": "2026-06-22T12:56:44.982Z"
    },
    {
      "id": "holding8",
      "symbol": "2376",
      "shares": 355,
      "avgCost": 244.22,
      "broker": "Mega",
      "account": "Default",
      "name": "技嘉",
      "market": "TWSE",
      "marketName": "上市",
      "yahooSymbol": "2376.TW",
      "sector": "電子",
      "currentPrice": 339.5,
      "previousClose": 344,
      "change": -4.5,
      "changePercent": -1.308139534883721,
      "eps": null,
      "pe": null,
      "forwardPe": null,
      "cost": 86698.1,
      "marketValue": 120522.5,
      "todayPnL": -1597.5,
      "unrealizedPnL": 33824.399999999994,
      "unrealizedPnLPct": 39.01400376709523,
      "weight": 4.5688372489740985,
      "dataStatus": "fundamentals_missing",
      "failedProviders": [
        "TPEX API: not TPEX",
        "Yahoo Finance: Yahoo fundamentals 2376 HTTP 401",
        "WantGoo: WantGoo fundamentals 2376 HTTP 403"
      ],
      "source": "Yahoo Finance chart",
      "updatedAt": "2026-06-22T12:56:45.001Z"
    },
    {
      "id": "holding9",
      "symbol": "2382",
      "shares": 180,
      "avgCost": 273.94,
      "broker": "Mega",
      "account": "Default",
      "name": "廣達",
      "market": "TWSE",
      "marketName": "上市",
      "yahooSymbol": "2382.TW",
      "sector": "電子",
      "currentPrice": 380,
      "previousClose": 376,
      "change": 4,
      "changePercent": 1.0638297872340425,
      "eps": null,
      "pe": null,
      "forwardPe": null,
      "cost": 49309.2,
      "marketValue": 68400,
      "todayPnL": 720,
      "unrealizedPnL": 19090.800000000003,
      "unrealizedPnLPct": 38.716507264364466,
      "weight": 2.5929471080489397,
      "dataStatus": "fundamentals_missing",
      "failedProviders": [
        "TPEX API: not TPEX",
        "Yahoo Finance: Yahoo fundamentals 2382 HTTP 401",
        "WantGoo: WantGoo fundamentals 2382 HTTP 403"
      ],
      "source": "Yahoo Finance chart",
      "updatedAt": "2026-06-22T12:56:45.082Z"
    },
    {
      "id": "holding10",
      "symbol": "2408",
      "shares": 50,
      "avgCost": 353,
      "broker": "Mega",
      "account": "Default",
      "name": "南亞科",
      "market": "TWSE",
      "marketName": "上市",
      "yahooSymbol": "2408.TW",
      "sector": "電子",
      "currentPrice": 505,
      "previousClose": 459.5,
      "change": 45.5,
      "changePercent": 9.902067464635474,
      "eps": null,
      "pe": null,
      "forwardPe": null,
      "cost": 17650,
      "marketValue": 25250,
      "todayPnL": 2275,
      "unrealizedPnL": 7600,
      "unrealizedPnLPct": 43.05949008498583,
      "weight": 0.9571917321379494,
      "dataStatus": "fundamentals_missing",
      "failedProviders": [
        "TPEX API: not TPEX",
        "Yahoo Finance: Yahoo fundamentals 2408 HTTP 401",
        "WantGoo: WantGoo fundamentals 2408 HTTP 403"
      ],
      "source": "Yahoo Finance chart",
      "updatedAt": "2026-06-22T12:56:45.158Z"
    },
    {
      "id": "holding11",
      "symbol": "2449",
      "shares": 100,
      "avgCost": 311.5,
      "broker": "Mega",
      "account": "Default",
      "name": "京元電子",
      "market": "TWSE",
      "marketName": "上市",
      "yahooSymbol": "2449.TW",
      "sector": "電子",
      "currentPrice": 339,
      "previousClose": 308.5,
      "change": 30.5,
      "changePercent": 9.886547811993516,
      "eps": null,
      "pe": null,
      "forwardPe": null,
      "cost": 31150,
      "marketValue": 33900,
      "todayPnL": 3050,
      "unrealizedPnL": 2750,
      "unrealizedPnLPct": 8.828250401284109,
      "weight": 1.2851009789891676,
      "dataStatus": "fundamentals_missing",
      "failedProviders": [
        "TPEX API: not TPEX",
        "Yahoo Finance: Yahoo fundamentals 2449 HTTP 401",
        "WantGoo: WantGoo fundamentals 2449 HTTP 403"
      ],
      "source": "Yahoo Finance chart",
      "updatedAt": "2026-06-22T12:56:45.157Z"
    },
    {
      "id": "holding12",
      "symbol": "2454",
      "shares": 5,
      "avgCost": 1455,
      "broker": "Mega",
      "account": "Default",
      "name": "聯發科",
      "market": "TWSE",
      "marketName": "上市",
      "yahooSymbol": "2454.TW",
      "sector": "電子",
      "currentPrice": 4465,
      "previousClose": 4390,
      "change": 75,
      "changePercent": 1.7084282460136675,
      "eps": null,
      "pe": null,
      "forwardPe": null,
      "cost": 7275,
      "marketValue": 22325,
      "todayPnL": 375,
      "unrealizedPnL": 15050,
      "unrealizedPnLPct": 206.872852233677,
      "weight": 0.8463091255437513,
      "dataStatus": "fundamentals_missing",
      "failedProviders": [
        "TPEX API: not TPEX",
        "Yahoo Finance: Yahoo fundamentals 2454 HTTP 401",
        "WantGoo: WantGoo fundamentals 2454 HTTP 403"
      ],
      "source": "Yahoo Finance chart",
      "updatedAt": "2026-06-22T12:56:45.311Z"
    },
    {
      "id": "holding13",
      "symbol": "2472",
      "shares": 100,
      "avgCost": 239,
      "broker": "Mega",
      "account": "Default",
      "name": "立隆電",
      "market": "TWSE",
      "marketName": "上市",
      "yahooSymbol": "2472.TW",
      "sector": "電子",
      "currentPrice": 393.5,
      "previousClose": 402,
      "change": -8.5,
      "changePercent": -2.1144278606965177,
      "eps": null,
      "pe": null,
      "forwardPe": null,
      "cost": 23900,
      "marketValue": 39350,
      "todayPnL": -850,
      "unrealizedPnL": 15450,
      "unrealizedPnLPct": 64.64435146443515,
      "weight": 1.4917027587971607,
      "dataStatus": "fundamentals_missing",
      "failedProviders": [
        "TPEX API: not TPEX",
        "Yahoo Finance: Yahoo fundamentals 2472 HTTP 401",
        "WantGoo: WantGoo fundamentals 2472 HTTP 403"
      ],
      "source": "Yahoo Finance chart",
      "updatedAt": "2026-06-22T12:56:45.219Z"
    },
    {
      "id": "holding14",
      "symbol": "2610",
      "shares": 1000,
      "avgCost": 19.3,
      "broker": "Mega",
      "account": "Default",
      "name": "華航",
      "market": "TWSE",
      "marketName": "上市",
      "yahooSymbol": "2610.TW",
      "sector": "航運",
      "currentPrice": 21.8,
      "previousClose": 22,
      "change": -0.1999999999999993,
      "changePercent": -0.909090909090906,
      "eps": null,
      "pe": null,
      "forwardPe": null,
      "cost": 19300,
      "marketValue": 21800,
      "todayPnL": -199.9999999999993,
      "unrealizedPnL": 2500,
      "unrealizedPnLPct": 12.953367875647666,
      "weight": 0.8264071192319721,
      "dataStatus": "fundamentals_missing",
      "failedProviders": [
        "TPEX API: not TPEX",
        "Yahoo Finance: Yahoo fundamentals 2610 HTTP 401",
        "WantGoo: WantGoo fundamentals 2610 HTTP 403"
      ],
      "source": "Yahoo Finance chart",
      "updatedAt": "2026-06-22T12:56:45.310Z"
    },
    {
      "id": "holding15",
      "symbol": "2884",
      "shares": 500,
      "avgCost": 32.35,
      "broker": "Mega",
      "account": "Default",
      "name": "玉山金",
      "market": "TWSE",
      "marketName": "上市",
      "yahooSymbol": "2884.TW",
      "sector": "金融",
      "currentPrice": 35.8,
      "previousClose": 35.400001525878906,
      "change": 0.3999984741210909,
      "changePercent": 1.1299391437276494,
      "eps": null,
      "pe": null,
      "forwardPe": null,
      "cost": 16175,
      "marketValue": 17900,
      "todayPnL": 199.99923706054545,
      "unrealizedPnL": 1725,
      "unrealizedPnLPct": 10.664605873261205,
      "weight": 0.6785636437730413,
      "dataStatus": "fundamentals_missing",
      "failedProviders": [
        "TPEX API: not TPEX",
        "Yahoo Finance: Yahoo fundamentals 2884 HTTP 401",
        "WantGoo: WantGoo fundamentals 2884 HTTP 403"
      ],
      "source": "Yahoo Finance chart",
      "updatedAt": "2026-06-22T12:56:45.393Z"
    },
    {
      "id": "holding16",
      "symbol": "2912",
      "shares": 200,
      "avgCost": 233.75,
      "broker": "Mega",
      "account": "Default",
      "name": "統一超",
      "market": "TWSE",
      "marketName": "上市",
      "yahooSymbol": "2912.TW",
      "sector": "其他",
      "currentPrice": 221,
      "previousClose": 223.5,
      "change": -2.5,
      "changePercent": -1.1185682326621924,
      "eps": null,
      "pe": null,
      "forwardPe": null,
      "cost": 46750,
      "marketValue": 44200,
      "todayPnL": -500,
      "unrealizedPnL": -2550,
      "unrealizedPnLPct": -5.454545454545454,
      "weight": 1.675559388534549,
      "dataStatus": "fundamentals_missing",
      "failedProviders": [
        "TPEX API: not TPEX",
        "Yahoo Finance: Yahoo fundamentals 2912 HTTP 401",
        "WantGoo: WantGoo fundamentals 2912 HTTP 403"
      ],
      "source": "Yahoo Finance chart",
      "updatedAt": "2026-06-22T12:56:45.445Z"
    },
    {
      "id": "holding17",
      "symbol": "3008",
      "shares": 2,
      "avgCost": 3240,
      "broker": "Mega",
      "account": "Default",
      "name": "大立光",
      "market": "TWSE",
      "marketName": "上市",
      "yahooSymbol": "3008.TW",
      "sector": "電子",
      "currentPrice": 5185,
      "previousClose": 5195,
      "change": -10,
      "changePercent": -0.192492781520693,
      "eps": null,
      "pe": null,
      "forwardPe": null,
      "cost": 6480,
      "marketValue": 10370,
      "todayPnL": -20,
      "unrealizedPnL": 3890,
      "unrealizedPnLPct": 60.03086419753087,
      "weight": 0.39311201038695187,
      "dataStatus": "fundamentals_missing",
      "failedProviders": [
        "TPEX API: not TPEX",
        "Yahoo Finance: Yahoo fundamentals 3008 HTTP 401",
        "WantGoo: WantGoo fundamentals 3008 HTTP 403"
      ],
      "source": "Yahoo Finance chart",
      "updatedAt": "2026-06-22T12:56:45.468Z"
    },
    {
      "id": "holding18",
      "symbol": "3163",
      "shares": 60,
      "avgCost": 606,
      "broker": "Mega",
      "account": "Default",
      "name": "波若威",
      "market": "TPEX",
      "marketName": "上櫃",
      "yahooSymbol": "3163.TWO",
      "sector": "通訊網路",
      "currentPrice": 870,
      "previousClose": 893,
      "change": -23,
      "changePercent": -2.57558790593505,
      "eps": null,
      "pe": null,
      "forwardPe": null,
      "cost": 36360,
      "marketValue": 52200,
      "todayPnL": -1380,
      "unrealizedPnL": 15840,
      "unrealizedPnLPct": 43.56435643564357,
      "weight": 1.978828056142612,
      "dataStatus": "fundamentals_missing",
      "failedProviders": [
        "TWSE OpenAPI: not TWSE",
        "TPEX API: TPEX fundamentals snapshot timeout",
        "Yahoo Finance: Yahoo fundamentals 3163 HTTP 401",
        "TradingView: TradingView 3163 HTTP 404",
        "WantGoo: WantGoo fundamentals 3163 HTTP 403"
      ],
      "source": "Yahoo Finance chart",
      "updatedAt": "2026-06-22T12:56:45.691Z"
    },
    {
      "id": "holding19",
      "symbol": "3227",
      "shares": 70,
      "avgCost": 226,
      "broker": "Mega",
      "account": "Default",
      "name": "3227",
      "market": "UNKNOWN",
      "marketName": "未知",
      "yahooSymbol": "3227.TW",
      "sector": "其他",
      "currentPrice": null,
      "previousClose": null,
      "change": null,
      "changePercent": null,
      "eps": null,
      "pe": null,
      "forwardPe": null,
      "cost": 15820,
      "marketValue": 0,
      "todayPnL": 0,
      "unrealizedPnL": -15820,
      "unrealizedPnLPct": -100,
      "weight": 0,
      "dataStatus": "resolver_failed",
      "failedProviders": [
        "Yahoo Finance chart: Yahoo chart 3227.TW HTTP 404",
        "Yahoo scraper: fetch failed",
        "TWSE API: not TWSE",
        "TPEX API: not TPEX",
        "TWSE public data: not TWSE",
        "WantGoo: WantGoo 3227 HTTP 403",
        "TWSE OpenAPI: not TWSE",
        "TPEX API: not TPEX",
        "Yahoo Finance: Yahoo fundamentals 3227 HTTP 401",
        "TradingView: TradingView 3227 HTTP 404",
        "WantGoo: WantGoo fundamentals 3227 HTTP 403"
      ],
      "source": null,
      "updatedAt": "2026-06-22T12:56:47.163Z"
    },
    {
      "id": "holding20",
      "symbol": "3231",
      "shares": 350,
      "avgCost": 151.14,
      "broker": "Mega",
      "account": "Default",
      "name": "緯創",
      "market": "TWSE",
      "marketName": "上市",
      "yahooSymbol": "3231.TW",
      "sector": "其他",
      "currentPrice": 162.5,
      "previousClose": 161.5,
      "change": 1,
      "changePercent": 0.6191950464396285,
      "eps": null,
      "pe": null,
      "forwardPe": null,
      "cost": 52898.99999999999,
      "marketValue": 56875,
      "todayPnL": 350,
      "unrealizedPnL": 3976.0000000000073,
      "unrealizedPnLPct": 7.516210136297487,
      "weight": 2.156050683776074,
      "dataStatus": "fundamentals_missing",
      "failedProviders": [
        "TPEX API: not TPEX",
        "Yahoo Finance: Yahoo fundamentals 3231 HTTP 401",
        "WantGoo: WantGoo fundamentals 3231 HTTP 403"
      ],
      "source": "Yahoo Finance chart",
      "updatedAt": "2026-06-22T12:56:47.038Z"
    },
    {
      "id": "holding21",
      "symbol": "3293",
      "shares": 25,
      "avgCost": 757,
      "broker": "Mega",
      "account": "Default",
      "name": "3293",
      "market": "UNKNOWN",
      "marketName": "未知",
      "yahooSymbol": "3293.TW",
      "sector": "其他",
      "currentPrice": null,
      "previousClose": null,
      "change": null,
      "changePercent": null,
      "eps": null,
      "pe": null,
      "forwardPe": null,
      "cost": 18925,
      "marketValue": 0,
      "todayPnL": 0,
      "unrealizedPnL": -18925,
      "unrealizedPnLPct": -100,
      "weight": 0,
      "dataStatus": "resolver_failed",
      "failedProviders": [
        "Yahoo Finance chart: Yahoo chart 3293.TW HTTP 404",
        "Yahoo scraper: fetch failed",
        "TWSE API: not TWSE",
        "TPEX API: not TPEX",
        "TWSE public data: not TWSE",
        "WantGoo: WantGoo 3293 HTTP 403",
        "TWSE OpenAPI: not TWSE",
        "TPEX API: not TPEX",
        "Yahoo Finance: Yahoo fundamentals 3293 HTTP 401",
        "TradingView: TradingView 3293 HTTP 404",
        "WantGoo: WantGoo fundamentals 3293 HTTP 403"
      ],
      "source": null,
      "updatedAt": "2026-06-22T12:56:49.061Z"
    },
    {
      "id": "holding22",
      "symbol": "3376",
      "shares": 30,
      "avgCost": 209,
      "broker": "Mega",
      "account": "Default",
      "name": "新日興",
      "market": "TWSE",
      "marketName": "上市",
      "yahooSymbol": "3376.TW",
      "sector": "其他",
      "currentPrice": 209,
      "previousClose": 205,
      "change": 4,
      "changePercent": 1.951219512195122,
      "eps": null,
      "pe": null,
      "forwardPe": null,
      "cost": 6270,
      "marketValue": 6270,
      "todayPnL": 120,
      "unrealizedPnL": 0,
      "unrealizedPnLPct": 0,
      "weight": 0.23768681823781948,
      "dataStatus": "fundamentals_missing",
      "failedProviders": [
        "TPEX API: not TPEX",
        "Yahoo Finance: Yahoo fundamentals 3376 HTTP 401",
        "WantGoo: WantGoo fundamentals 3376 HTTP 403"
      ],
      "source": "Yahoo Finance chart",
      "updatedAt": "2026-06-22T12:56:47.222Z"
    },
    {
      "id": "holding23",
      "symbol": "3533",
      "shares": 5,
      "avgCost": 2390,
      "broker": "Mega",
      "account": "Default",
      "name": "嘉澤",
      "market": "TWSE",
      "marketName": "上市",
      "yahooSymbol": "3533.TW",
      "sector": "其他",
      "currentPrice": 2315,
      "previousClose": 2290,
      "change": 25,
      "changePercent": 1.0917030567685588,
      "eps": null,
      "pe": null,
      "forwardPe": null,
      "cost": 11950,
      "marketValue": 11575,
      "todayPnL": 125,
      "unrealizedPnL": -375,
      "unrealizedPnLPct": -3.1380753138075312,
      "weight": 0.4387918534454163,
      "dataStatus": "fundamentals_missing",
      "failedProviders": [
        "TPEX API: not TPEX",
        "Yahoo Finance: Yahoo fundamentals 3533 HTTP 401",
        "WantGoo: WantGoo fundamentals 3533 HTTP 403"
      ],
      "source": "Yahoo Finance chart",
      "updatedAt": "2026-06-22T12:56:47.349Z"
    },
    {
      "id": "holding24",
      "symbol": "3583",
      "shares": 12,
      "avgCost": 843,
      "broker": "Mega",
      "account": "Default",
      "name": "辛耘",
      "market": "TWSE",
      "marketName": "上市",
      "yahooSymbol": "3583.TW",
      "sector": "其他",
      "currentPrice": 889,
      "previousClose": 889,
      "change": 0,
      "changePercent": 0,
      "eps": null,
      "pe": null,
      "forwardPe": null,
      "cost": 10116,
      "marketValue": 10668,
      "todayPnL": 0,
      "unrealizedPnL": 552,
      "unrealizedPnLPct": 5.456702253855279,
      "weight": 0.4044087682553522,
      "dataStatus": "fundamentals_missing",
      "failedProviders": [
        "TPEX API: not TPEX",
        "Yahoo Finance: Yahoo fundamentals 3583 HTTP 401",
        "WantGoo: WantGoo fundamentals 3583 HTTP 403"
      ],
      "source": "Yahoo Finance chart",
      "updatedAt": "2026-06-22T12:56:47.385Z"
    },
    {
      "id": "holding25",
      "symbol": "3665",
      "shares": 4,
      "avgCost": 2060,
      "broker": "Mega",
      "account": "Default",
      "name": "貿聯-KY",
      "market": "TWSE",
      "marketName": "上市",
      "yahooSymbol": "3665.TW",
      "sector": "電子",
      "currentPrice": 1990,
      "previousClose": 2100,
      "change": -110,
      "changePercent": -5.238095238095238,
      "eps": null,
      "pe": null,
      "forwardPe": null,
      "cost": 8240,
      "marketValue": 7960,
      "todayPnL": -440,
      "unrealizedPnL": -280,
      "unrealizedPnLPct": -3.3980582524271843,
      "weight": 0.3017523242700228,
      "dataStatus": "fundamentals_missing",
      "failedProviders": [
        "TPEX API: not TPEX",
        "Yahoo Finance: Yahoo fundamentals 3665 HTTP 401",
        "WantGoo: WantGoo fundamentals 3665 HTTP 403"
      ],
      "source": "Yahoo Finance chart",
      "updatedAt": "2026-06-22T12:56:47.437Z"
    },
    {
      "id": "holding26",
      "symbol": "3711",
      "shares": 125,
      "avgCost": 366.08,
      "broker": "Mega",
      "account": "Default",
      "name": "日月光投控",
      "market": "TWSE",
      "marketName": "上市",
      "yahooSymbol": "3711.TW",
      "sector": "其他",
      "currentPrice": 674,
      "previousClose": 613,
      "change": 61,
      "changePercent": 9.9510603588907,
      "eps": null,
      "pe": null,
      "forwardPe": null,
      "cost": 45760,
      "marketValue": 84250,
      "todayPnL": 7625,
      "unrealizedPnL": 38490,
      "unrealizedPnLPct": 84.11276223776224,
      "weight": 3.1937981557474155,
      "dataStatus": "fundamentals_missing",
      "failedProviders": [
        "TPEX API: not TPEX",
        "Yahoo Finance: Yahoo fundamentals 3711 HTTP 401",
        "WantGoo: WantGoo fundamentals 3711 HTTP 403"
      ],
      "source": "Yahoo Finance chart",
      "updatedAt": "2026-06-22T12:56:47.571Z"
    },
    {
      "id": "holding27",
      "symbol": "4979",
      "shares": 108,
      "avgCost": 329.35,
      "broker": "Mega",
      "account": "Default",
      "name": "4979",
      "market": "UNKNOWN",
      "marketName": "未知",
      "yahooSymbol": "4979.TW",
      "sector": "其他",
      "currentPrice": null,
      "previousClose": null,
      "change": null,
      "changePercent": null,
      "eps": null,
      "pe": null,
      "forwardPe": null,
      "cost": 35569.8,
      "marketValue": 0,
      "todayPnL": 0,
      "unrealizedPnL": -35569.8,
      "unrealizedPnLPct": -100,
      "weight": 0,
      "dataStatus": "resolver_failed",
      "failedProviders": [
        "Yahoo Finance chart: Yahoo chart 4979.TW HTTP 404",
        "Yahoo scraper: fetch failed",
        "TWSE API: not TWSE",
        "TPEX API: not TPEX",
        "TWSE public data: not TWSE",
        "WantGoo: WantGoo 4979 HTTP 403",
        "TWSE OpenAPI: not TWSE",
        "TPEX API: not TPEX",
        "Yahoo Finance: Yahoo fundamentals 4979 HTTP 401",
        "TradingView: TradingView 4979 HTTP 404",
        "WantGoo: WantGoo fundamentals 4979 HTTP 403"
      ],
      "source": null,
      "updatedAt": "2026-06-22T12:56:50.595Z"
    },
    {
      "id": "holding28",
      "symbol": "5439",
      "shares": 100,
      "avgCost": 298,
      "broker": "Mega",
      "account": "Default",
      "name": "5439",
      "market": "UNKNOWN",
      "marketName": "未知",
      "yahooSymbol": "5439.TW",
      "sector": "其他",
      "currentPrice": null,
      "previousClose": null,
      "change": null,
      "changePercent": null,
      "eps": null,
      "pe": null,
      "forwardPe": null,
      "cost": 29800,
      "marketValue": 0,
      "todayPnL": 0,
      "unrealizedPnL": -29800,
      "unrealizedPnLPct": -100,
      "weight": 0,
      "dataStatus": "resolver_failed",
      "failedProviders": [
        "Yahoo Finance chart: Yahoo chart 5439.TW HTTP 404",
        "Yahoo scraper: fetch failed",
        "TWSE API: not TWSE",
        "TPEX API: not TPEX",
        "TWSE public data: not TWSE",
        "WantGoo: WantGoo 5439 HTTP 403",
        "TWSE OpenAPI: not TWSE",
        "TPEX API: not TPEX",
        "Yahoo Finance: Yahoo fundamentals 5439 HTTP 401",
        "TradingView: TradingView 5439 HTTP 404",
        "WantGoo: WantGoo fundamentals 5439 HTTP 403"
      ],
      "source": null,
      "updatedAt": "2026-06-22T12:56:52.364Z"
    },
    {
      "id": "holding29",
      "symbol": "6187",
      "shares": 10,
      "avgCost": 1080,
      "broker": "Mega",
      "account": "Default",
      "name": "6187",
      "market": "UNKNOWN",
      "marketName": "未知",
      "yahooSymbol": "6187.TW",
      "sector": "其他",
      "currentPrice": null,
      "previousClose": null,
      "change": null,
      "changePercent": null,
      "eps": null,
      "pe": null,
      "forwardPe": null,
      "cost": 10800,
      "marketValue": 0,
      "todayPnL": 0,
      "unrealizedPnL": -10800,
      "unrealizedPnLPct": -100,
      "weight": 0,
      "dataStatus": "resolver_failed",
      "failedProviders": [
        "Yahoo Finance chart: Yahoo chart 6187.TW HTTP 404",
        "Yahoo scraper: fetch failed",
        "TWSE API: not TWSE",
        "TPEX API: not TPEX",
        "TWSE public data: not TWSE",
        "WantGoo: WantGoo 6187 HTTP 403",
        "TWSE OpenAPI: not TWSE",
        "TPEX API: not TPEX",
        "Yahoo Finance: Yahoo fundamentals 6187 HTTP 401",
        "TradingView: TradingView 6187 HTTP 404",
        "WantGoo: WantGoo fundamentals 6187 HTTP 403"
      ],
      "source": null,
      "updatedAt": "2026-06-22T12:56:53.811Z"
    },
    {
      "id": "holding30",
      "symbol": "6197",
      "shares": 170,
      "avgCost": 134.71,
      "broker": "Mega",
      "account": "Default",
      "name": "佳必琪",
      "market": "TWSE",
      "marketName": "上市",
      "yahooSymbol": "6197.TW",
      "sector": "其他",
      "currentPrice": 353,
      "previousClose": 347.5,
      "change": 5.5,
      "changePercent": 1.5827338129496402,
      "eps": null,
      "pe": null,
      "forwardPe": null,
      "cost": 22900.7,
      "marketValue": 60010,
      "todayPnL": 935,
      "unrealizedPnL": 37109.3,
      "unrealizedPnLPct": 162.04439165615025,
      "weight": 2.2748940928949835,
      "dataStatus": "fundamentals_missing",
      "failedProviders": [
        "TPEX API: not TPEX",
        "Yahoo Finance: Yahoo fundamentals 6197 HTTP 401",
        "WantGoo: WantGoo fundamentals 6197 HTTP 403"
      ],
      "source": "Yahoo Finance chart",
      "updatedAt": "2026-06-22T12:56:52.475Z"
    },
    {
      "id": "holding31",
      "symbol": "6239",
      "shares": 120,
      "avgCost": 152.92,
      "broker": "Mega",
      "account": "Default",
      "name": "力成",
      "market": "TWSE",
      "marketName": "上市",
      "yahooSymbol": "6239.TW",
      "sector": "其他",
      "currentPrice": 366,
      "previousClose": 363.5,
      "change": 2.5,
      "changePercent": 0.6877579092159559,
      "eps": null,
      "pe": null,
      "forwardPe": null,
      "cost": 18350.399999999998,
      "marketValue": 43920,
      "todayPnL": 300,
      "unrealizedPnL": 25569.600000000002,
      "unrealizedPnLPct": 139.34083180748107,
      "weight": 1.6649449851682665,
      "dataStatus": "fundamentals_missing",
      "failedProviders": [
        "TPEX API: not TPEX",
        "Yahoo Finance: Yahoo fundamentals 6239 HTTP 401",
        "WantGoo: WantGoo fundamentals 6239 HTTP 403"
      ],
      "source": "Yahoo Finance chart",
      "updatedAt": "2026-06-22T12:56:52.610Z"
    },
    {
      "id": "holding32",
      "symbol": "6274",
      "shares": 15,
      "avgCost": 513,
      "broker": "Mega",
      "account": "Default",
      "name": "6274",
      "market": "UNKNOWN",
      "marketName": "未知",
      "yahooSymbol": "6274.TW",
      "sector": "其他",
      "currentPrice": null,
      "previousClose": null,
      "change": null,
      "changePercent": null,
      "eps": null,
      "pe": null,
      "forwardPe": null,
      "cost": 7695,
      "marketValue": 0,
      "todayPnL": 0,
      "unrealizedPnL": -7695,
      "unrealizedPnLPct": -100,
      "weight": 0,
      "dataStatus": "resolver_failed",
      "failedProviders": [
        "Yahoo Finance chart: Yahoo chart 6274.TW HTTP 404",
        "Yahoo scraper: fetch failed",
        "TWSE API: not TWSE",
        "TPEX API: not TPEX",
        "TWSE public data: not TWSE",
        "WantGoo: WantGoo 6274 HTTP 403",
        "TWSE OpenAPI: not TWSE",
        "TPEX API: not TPEX",
        "Yahoo Finance: Yahoo fundamentals 6274 HTTP 401",
        "TradingView: TradingView 6274 HTTP 404",
        "WantGoo: WantGoo fundamentals 6274 HTTP 403"
      ],
      "source": null,
      "updatedAt": "2026-06-22T12:56:54.137Z"
    },
    {
      "id": "holding33",
      "symbol": "6510",
      "shares": 4,
      "avgCost": 3525,
      "broker": "Mega",
      "account": "Default",
      "name": "6510",
      "market": "UNKNOWN",
      "marketName": "未知",
      "yahooSymbol": "6510.TW",
      "sector": "其他",
      "currentPrice": null,
      "previousClose": null,
      "change": null,
      "changePercent": null,
      "eps": null,
      "pe": null,
      "forwardPe": null,
      "cost": 14100,
      "marketValue": 0,
      "todayPnL": 0,
      "unrealizedPnL": -14100,
      "unrealizedPnLPct": -100,
      "weight": 0,
      "dataStatus": "resolver_failed",
      "failedProviders": [
        "Yahoo Finance chart: Yahoo chart 6510.TW HTTP 404",
        "Yahoo scraper: fetch failed",
        "TWSE API: not TWSE",
        "TPEX API: not TPEX",
        "TWSE public data: not TWSE",
        "WantGoo: WantGoo 6510 HTTP 403",
        "TWSE OpenAPI: not TWSE",
        "TPEX API: not TPEX",
        "Yahoo Finance: Yahoo fundamentals 6510 HTTP 401",
        "TradingView: TradingView 6510 HTTP 404",
        "WantGoo: WantGoo fundamentals 6510 HTTP 403"
      ],
      "source": null,
      "updatedAt": "2026-06-22T12:56:54.734Z"
    },
    {
      "id": "holding34",
      "symbol": "6640",
      "shares": 18,
      "avgCost": 738,
      "broker": "Mega",
      "account": "Default",
      "name": "6640",
      "market": "UNKNOWN",
      "marketName": "未知",
      "yahooSymbol": "6640.TW",
      "sector": "其他",
      "currentPrice": null,
      "previousClose": null,
      "change": null,
      "changePercent": null,
      "eps": null,
      "pe": null,
      "forwardPe": null,
      "cost": 13284,
      "marketValue": 0,
      "todayPnL": 0,
      "unrealizedPnL": -13284,
      "unrealizedPnLPct": -100,
      "weight": 0,
      "dataStatus": "resolver_failed",
      "failedProviders": [
        "Yahoo Finance chart: Yahoo chart 6640.TW HTTP 404",
        "Yahoo scraper: fetch failed",
        "TWSE API: not TWSE",
        "TPEX API: not TPEX",
        "TWSE public data: not TWSE",
        "WantGoo: WantGoo 6640 HTTP 403",
        "TWSE OpenAPI: not TWSE",
        "TPEX API: not TPEX",
        "Yahoo Finance: Yahoo fundamentals 6640 HTTP 401",
        "TradingView: TradingView 6640 HTTP 404",
        "WantGoo: WantGoo fundamentals 6640 HTTP 403"
      ],
      "source": null,
      "updatedAt": "2026-06-22T12:56:55.418Z"
    },
    {
      "id": "holding35",
      "symbol": "6830",
      "shares": 13,
      "avgCost": 740.77,
      "broker": "Mega",
      "account": "Default",
      "name": "汎銓",
      "market": "TWSE",
      "marketName": "上市",
      "yahooSymbol": "6830.TW",
      "sector": "其他",
      "currentPrice": 608,
      "previousClose": 564,
      "change": 44,
      "changePercent": 7.801418439716312,
      "eps": null,
      "pe": null,
      "forwardPe": null,
      "cost": 9630.01,
      "marketValue": 7904,
      "todayPnL": 572,
      "unrealizedPnL": -1726.0100000000002,
      "unrealizedPnLPct": -17.92324203193974,
      "weight": 0.2996294435967664,
      "dataStatus": "fundamentals_missing",
      "failedProviders": [
        "TPEX API: not TPEX",
        "Yahoo Finance: Yahoo fundamentals 6830 HTTP 401",
        "WantGoo: WantGoo fundamentals 6830 HTTP 403"
      ],
      "source": "Yahoo Finance chart",
      "updatedAt": "2026-06-22T12:56:54.853Z"
    },
    {
      "id": "holding36",
      "symbol": "7769",
      "shares": 4,
      "avgCost": 7660,
      "broker": "Mega",
      "account": "Default",
      "name": "鴻勁",
      "market": "TWSE",
      "marketName": "上市",
      "yahooSymbol": "7769.TW",
      "sector": "其他",
      "currentPrice": 6915,
      "previousClose": 6975,
      "change": -60,
      "changePercent": -0.8602150537634409,
      "eps": null,
      "pe": null,
      "forwardPe": null,
      "cost": 30640,
      "marketValue": 27660,
      "todayPnL": -240,
      "unrealizedPnL": -2980,
      "unrealizedPnLPct": -9.725848563968668,
      "weight": 1.0485514182548783,
      "dataStatus": "fundamentals_missing",
      "failedProviders": [
        "TPEX API: not TPEX",
        "Yahoo Finance: Yahoo fundamentals 7769 HTTP 401",
        "WantGoo: WantGoo fundamentals 7769 HTTP 403"
      ],
      "source": "Yahoo Finance chart",
      "updatedAt": "2026-06-22T12:56:54.952Z"
    },
    {
      "id": "holding37",
      "symbol": "7801",
      "shares": 3,
      "avgCost": 196.33,
      "broker": "Mega",
      "account": "Default",
      "name": "7801",
      "market": "UNKNOWN",
      "marketName": "未知",
      "yahooSymbol": "7801.TW",
      "sector": "其他",
      "currentPrice": null,
      "previousClose": null,
      "change": null,
      "changePercent": null,
      "eps": null,
      "pe": null,
      "forwardPe": null,
      "cost": 588.99,
      "marketValue": 0,
      "todayPnL": 0,
      "unrealizedPnL": -588.99,
      "unrealizedPnLPct": -100,
      "weight": 0,
      "dataStatus": "resolver_failed",
      "failedProviders": [
        "Yahoo Finance chart: Yahoo chart 7801.TW HTTP 404",
        "Yahoo scraper: fetch failed",
        "TWSE API: not TWSE",
        "TPEX API: not TPEX",
        "TWSE public data: not TWSE",
        "WantGoo: WantGoo 7801 HTTP 403",
        "TWSE OpenAPI: not TWSE",
        "TPEX API: not TPEX",
        "Yahoo Finance: Yahoo fundamentals 7801 HTTP 401",
        "TradingView: TradingView 7801 HTTP 404",
        "WantGoo: WantGoo fundamentals 7801 HTTP 403"
      ],
      "source": null,
      "updatedAt": "2026-06-22T12:56:56.535Z"
    },
    {
      "id": "holding38",
      "symbol": "8299",
      "shares": 2,
      "avgCost": 1770,
      "broker": "Mega",
      "account": "Default",
      "name": "8299",
      "market": "UNKNOWN",
      "marketName": "未知",
      "yahooSymbol": "8299.TW",
      "sector": "其他",
      "currentPrice": null,
      "previousClose": null,
      "change": null,
      "changePercent": null,
      "eps": null,
      "pe": null,
      "forwardPe": null,
      "cost": 3540,
      "marketValue": 0,
      "todayPnL": 0,
      "unrealizedPnL": -3540,
      "unrealizedPnLPct": -100,
      "weight": 0,
      "dataStatus": "resolver_failed",
      "failedProviders": [
        "Yahoo Finance chart: Yahoo chart 8299.TW HTTP 404",
        "Yahoo scraper: fetch failed",
        "TWSE API: not TWSE",
        "TPEX API: not TPEX",
        "TWSE public data: not TWSE",
        "WantGoo: WantGoo 8299 HTTP 403",
        "TWSE OpenAPI: not TWSE",
        "TPEX API: not TPEX",
        "Yahoo Finance: Yahoo fundamentals 8299 HTTP 401",
        "TradingView: TradingView 8299 HTTP 404",
        "WantGoo: WantGoo fundamentals 8299 HTTP 403"
      ],
      "source": null,
      "updatedAt": "2026-06-22T12:56:57.393Z"
    }
  ],
  "analytics": {
    "totalAssets": 2637925,
    "todayPnL": 28515.498626708984,
    "unrealizedPnL": 339388.2,
    "unrealizedPnLPct": 28.12548479613039,
    "winRate": 57.89473684210527,
    "holdingsCount": 38,
    "cash": 1091844,
    "cashRatio": 41.39025938948227,
    "largestHolding": {
      "id": "holding6",
      "symbol": "2330",
      "shares": 175,
      "avgCost": 1855,
      "broker": "Mega",
      "account": "Default",
      "name": "台積電",
      "market": "TWSE",
      "marketName": "上市",
      "yahooSymbol": "2330.TW",
      "sector": "電子",
      "currentPrice": 2510,
      "previousClose": 2410,
      "change": 100,
      "changePercent": 4.149377593360995,
      "eps": null,
      "pe": null,
      "forwardPe": null,
      "cost": 324625,
      "marketValue": 439250,
      "todayPnL": 17500,
      "unrealizedPnL": 114625,
      "unrealizedPnLPct": 35.309973045822105,
      "weight": 16.651345280855217,
      "dataStatus": "fundamentals_missing",
      "failedProviders": [
        "TPEX API: not TPEX",
        "Yahoo Finance: Yahoo fundamentals 2330 HTTP 401",
        "WantGoo: WantGoo fundamentals 2330 HTTP 403"
      ],
      "source": "Yahoo Finance chart",
      "updatedAt": "2026-06-22T12:56:44.879Z"
    },
    "largestWinner": {
      "id": "holding5",
      "symbol": "2327",
      "shares": 160,
      "avgCost": 281.13,
      "broker": "Mega",
      "account": "Default",
      "name": "國巨*",
      "market": "TWSE",
      "marketName": "上市",
      "yahooSymbol": "2327.TW",
      "sector": "電子",
      "currentPrice": 1065,
      "previousClose": 1080,
      "change": -15,
      "changePercent": -1.3888888888888888,
      "eps": null,
      "pe": null,
      "forwardPe": null,
      "cost": 44980.8,
      "marketValue": 170400,
      "todayPnL": -2400,
      "unrealizedPnL": 125419.2,
      "unrealizedPnLPct": 278.8283000746985,
      "weight": 6.4596226200517455,
      "dataStatus": "fundamentals_missing",
      "failedProviders": [
        "TPEX API: not TPEX",
        "Yahoo Finance: Yahoo fundamentals 2327 HTTP 401",
        "WantGoo: WantGoo fundamentals 2327 HTTP 403"
      ],
      "source": "Yahoo Finance chart",
      "updatedAt": "2026-06-22T12:56:44.896Z"
    },
    "largestLoser": {
      "id": "holding27",
      "symbol": "4979",
      "shares": 108,
      "avgCost": 329.35,
      "broker": "Mega",
      "account": "Default",
      "name": "4979",
      "market": "UNKNOWN",
      "marketName": "未知",
      "yahooSymbol": "4979.TW",
      "sector": "其他",
      "currentPrice": null,
      "previousClose": null,
      "change": null,
      "changePercent": null,
      "eps": null,
      "pe": null,
      "forwardPe": null,
      "cost": 35569.8,
      "marketValue": 0,
      "todayPnL": 0,
      "unrealizedPnL": -35569.8,
      "unrealizedPnLPct": -100,
      "weight": 0,
      "dataStatus": "resolver_failed",
      "failedProviders": [
        "Yahoo Finance chart: Yahoo chart 4979.TW HTTP 404",
        "Yahoo scraper: fetch failed",
        "TWSE API: not TWSE",
        "TPEX API: not TPEX",
        "TWSE public data: not TWSE",
        "WantGoo: WantGoo 4979 HTTP 403",
        "TWSE OpenAPI: not TWSE",
        "TPEX API: not TPEX",
        "Yahoo Finance: Yahoo fundamentals 4979 HTTP 401",
        "TradingView: TradingView 4979 HTTP 404",
        "WantGoo: WantGoo fundamentals 4979 HTTP 403"
      ],
      "source": null,
      "updatedAt": "2026-06-22T12:56:50.595Z"
    },
    "sectorAllocation": [
      {
        "name": "Cash",
        "value": 1091844,
        "weight": 41.39025938948227
      },
      {
        "name": "電子",
        "value": 1078619,
        "weight": 40.88891837334268
      },
      {
        "name": "其他",
        "value": 353332,
        "weight": 13.394315607911523
      },
      {
        "name": "通訊網路",
        "value": 52200,
        "weight": 1.978828056142612
      },
      {
        "name": "ETF",
        "value": 22230,
        "weight": 0.8427078101159055
      },
      {
        "name": "航運",
        "value": 21800,
        "weight": 0.8264071192319721
      },
      {
        "name": "金融",
        "value": 17900,
        "weight": 0.6785636437730413
      }
    ],
    "pnlRanking": [
      {
        "id": "holding5",
        "symbol": "2327",
        "shares": 160,
        "avgCost": 281.13,
        "broker": "Mega",
        "account": "Default",
        "name": "國巨*",
        "market": "TWSE",
        "marketName": "上市",
        "yahooSymbol": "2327.TW",
        "sector": "電子",
        "currentPrice": 1065,
        "previousClose": 1080,
        "change": -15,
        "changePercent": -1.3888888888888888,
        "eps": null,
        "pe": null,
        "forwardPe": null,
        "cost": 44980.8,
        "marketValue": 170400,
        "todayPnL": -2400,
        "unrealizedPnL": 125419.2,
        "unrealizedPnLPct": 278.8283000746985,
        "weight": 6.4596226200517455,
        "dataStatus": "fundamentals_missing",
        "failedProviders": [
          "TPEX API: not TPEX",
          "Yahoo Finance: Yahoo fundamentals 2327 HTTP 401",
          "WantGoo: WantGoo fundamentals 2327 HTTP 403"
        ],
        "source": "Yahoo Finance chart",
        "updatedAt": "2026-06-22T12:56:44.896Z"
      },
      {
        "id": "holding6",
        "symbol": "2330",
        "shares": 175,
        "avgCost": 1855,
        "broker": "Mega",
        "account": "Default",
        "name": "台積電",
        "market": "TWSE",
        "marketName": "上市",
        "yahooSymbol": "2330.TW",
        "sector": "電子",
        "currentPrice": 2510,
        "previousClose": 2410,
        "change": 100,
        "changePercent": 4.149377593360995,
        "eps": null,
        "pe": null,
        "forwardPe": null,
        "cost": 324625,
        "marketValue": 439250,
        "todayPnL": 17500,
        "unrealizedPnL": 114625,
        "unrealizedPnLPct": 35.309973045822105,
        "weight": 16.651345280855217,
        "dataStatus": "fundamentals_missing",
        "failedProviders": [
          "TPEX API: not TPEX",
          "Yahoo Finance: Yahoo fundamentals 2330 HTTP 401",
          "WantGoo: WantGoo fundamentals 2330 HTTP 403"
        ],
        "source": "Yahoo Finance chart",
        "updatedAt": "2026-06-22T12:56:44.879Z"
      },
      {
        "id": "holding26",
        "symbol": "3711",
        "shares": 125,
        "avgCost": 366.08,
        "broker": "Mega",
        "account": "Default",
        "name": "日月光投控",
        "market": "TWSE",
        "marketName": "上市",
        "yahooSymbol": "3711.TW",
        "sector": "其他",
        "currentPrice": 674,
        "previousClose": 613,
        "change": 61,
        "changePercent": 9.9510603588907,
        "eps": null,
        "pe": null,
        "forwardPe": null,
        "cost": 45760,
        "marketValue": 84250,
        "todayPnL": 7625,
        "unrealizedPnL": 38490,
        "unrealizedPnLPct": 84.11276223776224,
        "weight": 3.1937981557474155,
        "dataStatus": "fundamentals_missing",
        "failedProviders": [
          "TPEX API: not TPEX",
          "Yahoo Finance: Yahoo fundamentals 3711 HTTP 401",
          "WantGoo: WantGoo fundamentals 3711 HTTP 403"
        ],
        "source": "Yahoo Finance chart",
        "updatedAt": "2026-06-22T12:56:47.571Z"
      },
      {
        "id": "holding30",
        "symbol": "6197",
        "shares": 170,
        "avgCost": 134.71,
        "broker": "Mega",
        "account": "Default",
        "name": "佳必琪",
        "market": "TWSE",
        "marketName": "上市",
        "yahooSymbol": "6197.TW",
        "sector": "其他",
        "currentPrice": 353,
        "previousClose": 347.5,
        "change": 5.5,
        "changePercent": 1.5827338129496402,
        "eps": null,
        "pe": null,
        "forwardPe": null,
        "cost": 22900.7,
        "marketValue": 60010,
        "todayPnL": 935,
        "unrealizedPnL": 37109.3,
        "unrealizedPnLPct": 162.04439165615025,
        "weight": 2.2748940928949835,
        "dataStatus": "fundamentals_missing",
        "failedProviders": [
          "TPEX API: not TPEX",
          "Yahoo Finance: Yahoo fundamentals 6197 HTTP 401",
          "WantGoo: WantGoo fundamentals 6197 HTTP 403"
        ],
        "source": "Yahoo Finance chart",
        "updatedAt": "2026-06-22T12:56:52.475Z"
      },
      {
        "id": "holding8",
        "symbol": "2376",
        "shares": 355,
        "avgCost": 244.22,
        "broker": "Mega",
        "account": "Default",
        "name": "技嘉",
        "market": "TWSE",
        "marketName": "上市",
        "yahooSymbol": "2376.TW",
        "sector": "電子",
        "currentPrice": 339.5,
        "previousClose": 344,
        "change": -4.5,
        "changePercent": -1.308139534883721,
        "eps": null,
        "pe": null,
        "forwardPe": null,
        "cost": 86698.1,
        "marketValue": 120522.5,
        "todayPnL": -1597.5,
        "unrealizedPnL": 33824.399999999994,
        "unrealizedPnLPct": 39.01400376709523,
        "weight": 4.5688372489740985,
        "dataStatus": "fundamentals_missing",
        "failedProviders": [
          "TPEX API: not TPEX",
          "Yahoo Finance: Yahoo fundamentals 2376 HTTP 401",
          "WantGoo: WantGoo fundamentals 2376 HTTP 403"
        ],
        "source": "Yahoo Finance chart",
        "updatedAt": "2026-06-22T12:56:45.001Z"
      },
      {
        "id": "holding31",
        "symbol": "6239",
        "shares": 120,
        "avgCost": 152.92,
        "broker": "Mega",
        "account": "Default",
        "name": "力成",
        "market": "TWSE",
        "marketName": "上市",
        "yahooSymbol": "6239.TW",
        "sector": "其他",
        "currentPrice": 366,
        "previousClose": 363.5,
        "change": 2.5,
        "changePercent": 0.6877579092159559,
        "eps": null,
        "pe": null,
        "forwardPe": null,
        "cost": 18350.399999999998,
        "marketValue": 43920,
        "todayPnL": 300,
        "unrealizedPnL": 25569.600000000002,
        "unrealizedPnLPct": 139.34083180748107,
        "weight": 1.6649449851682665,
        "dataStatus": "fundamentals_missing",
        "failedProviders": [
          "TPEX API: not TPEX",
          "Yahoo Finance: Yahoo fundamentals 6239 HTTP 401",
          "WantGoo: WantGoo fundamentals 6239 HTTP 403"
        ],
        "source": "Yahoo Finance chart",
        "updatedAt": "2026-06-22T12:56:52.610Z"
      },
      {
        "id": "holding4",
        "symbol": "2317",
        "shares": 400,
        "avgCost": 218.53,
        "broker": "Mega",
        "account": "Default",
        "name": "鴻海",
        "market": "TWSE",
        "marketName": "上市",
        "yahooSymbol": "2317.TW",
        "sector": "電子",
        "currentPrice": 268.5,
        "previousClose": 268.5,
        "change": 0,
        "changePercent": 0,
        "eps": null,
        "pe": null,
        "forwardPe": null,
        "cost": 87412,
        "marketValue": 107400,
        "todayPnL": 0,
        "unrealizedPnL": 19988,
        "unrealizedPnLPct": 22.86642566238045,
        "weight": 4.071381862638248,
        "dataStatus": "fundamentals_missing",
        "failedProviders": [
          "TPEX API: not TPEX",
          "Yahoo Finance: Yahoo fundamentals 2317 HTTP 401",
          "WantGoo: WantGoo fundamentals 2317 HTTP 403"
        ],
        "source": "Yahoo Finance chart",
        "updatedAt": "2026-06-22T12:56:44.882Z"
      },
      {
        "id": "holding9",
        "symbol": "2382",
        "shares": 180,
        "avgCost": 273.94,
        "broker": "Mega",
        "account": "Default",
        "name": "廣達",
        "market": "TWSE",
        "marketName": "上市",
        "yahooSymbol": "2382.TW",
        "sector": "電子",
        "currentPrice": 380,
        "previousClose": 376,
        "change": 4,
        "changePercent": 1.0638297872340425,
        "eps": null,
        "pe": null,
        "forwardPe": null,
        "cost": 49309.2,
        "marketValue": 68400,
        "todayPnL": 720,
        "unrealizedPnL": 19090.800000000003,
        "unrealizedPnLPct": 38.716507264364466,
        "weight": 2.5929471080489397,
        "dataStatus": "fundamentals_missing",
        "failedProviders": [
          "TPEX API: not TPEX",
          "Yahoo Finance: Yahoo fundamentals 2382 HTTP 401",
          "WantGoo: WantGoo fundamentals 2382 HTTP 403"
        ],
        "source": "Yahoo Finance chart",
        "updatedAt": "2026-06-22T12:56:45.082Z"
      },
      {
        "id": "holding18",
        "symbol": "3163",
        "shares": 60,
        "avgCost": 606,
        "broker": "Mega",
        "account": "Default",
        "name": "波若威",
        "market": "TPEX",
        "marketName": "上櫃",
        "yahooSymbol": "3163.TWO",
        "sector": "通訊網路",
        "currentPrice": 870,
        "previousClose": 893,
        "change": -23,
        "changePercent": -2.57558790593505,
        "eps": null,
        "pe": null,
        "forwardPe": null,
        "cost": 36360,
        "marketValue": 52200,
        "todayPnL": -1380,
        "unrealizedPnL": 15840,
        "unrealizedPnLPct": 43.56435643564357,
        "weight": 1.978828056142612,
        "dataStatus": "fundamentals_missing",
        "failedProviders": [
          "TWSE OpenAPI: not TWSE",
          "TPEX API: TPEX fundamentals snapshot timeout",
          "Yahoo Finance: Yahoo fundamentals 3163 HTTP 401",
          "TradingView: TradingView 3163 HTTP 404",
          "WantGoo: WantGoo fundamentals 3163 HTTP 403"
        ],
        "source": "Yahoo Finance chart",
        "updatedAt": "2026-06-22T12:56:45.691Z"
      },
      {
        "id": "holding13",
        "symbol": "2472",
        "shares": 100,
        "avgCost": 239,
        "broker": "Mega",
        "account": "Default",
        "name": "立隆電",
        "market": "TWSE",
        "marketName": "上市",
        "yahooSymbol": "2472.TW",
        "sector": "電子",
        "currentPrice": 393.5,
        "previousClose": 402,
        "change": -8.5,
        "changePercent": -2.1144278606965177,
        "eps": null,
        "pe": null,
        "forwardPe": null,
        "cost": 23900,
        "marketValue": 39350,
        "todayPnL": -850,
        "unrealizedPnL": 15450,
        "unrealizedPnLPct": 64.64435146443515,
        "weight": 1.4917027587971607,
        "dataStatus": "fundamentals_missing",
        "failedProviders": [
          "TPEX API: not TPEX",
          "Yahoo Finance: Yahoo fundamentals 2472 HTTP 401",
          "WantGoo: WantGoo fundamentals 2472 HTTP 403"
        ],
        "source": "Yahoo Finance chart",
        "updatedAt": "2026-06-22T12:56:45.219Z"
      },
      {
        "id": "holding12",
        "symbol": "2454",
        "shares": 5,
        "avgCost": 1455,
        "broker": "Mega",
        "account": "Default",
        "name": "聯發科",
        "market": "TWSE",
        "marketName": "上市",
        "yahooSymbol": "2454.TW",
        "sector": "電子",
        "currentPrice": 4465,
        "previousClose": 4390,
        "change": 75,
        "changePercent": 1.7084282460136675,
        "eps": null,
        "pe": null,
        "forwardPe": null,
        "cost": 7275,
        "marketValue": 22325,
        "todayPnL": 375,
        "unrealizedPnL": 15050,
        "unrealizedPnLPct": 206.872852233677,
        "weight": 0.8463091255437513,
        "dataStatus": "fundamentals_missing",
        "failedProviders": [
          "TPEX API: not TPEX",
          "Yahoo Finance: Yahoo fundamentals 2454 HTTP 401",
          "WantGoo: WantGoo fundamentals 2454 HTTP 403"
        ],
        "source": "Yahoo Finance chart",
        "updatedAt": "2026-06-22T12:56:45.311Z"
      },
      {
        "id": "holding10",
        "symbol": "2408",
        "shares": 50,
        "avgCost": 353,
        "broker": "Mega",
        "account": "Default",
        "name": "南亞科",
        "market": "TWSE",
        "marketName": "上市",
        "yahooSymbol": "2408.TW",
        "sector": "電子",
        "currentPrice": 505,
        "previousClose": 459.5,
        "change": 45.5,
        "changePercent": 9.902067464635474,
        "eps": null,
        "pe": null,
        "forwardPe": null,
        "cost": 17650,
        "marketValue": 25250,
        "todayPnL": 2275,
        "unrealizedPnL": 7600,
        "unrealizedPnLPct": 43.05949008498583,
        "weight": 0.9571917321379494,
        "dataStatus": "fundamentals_missing",
        "failedProviders": [
          "TPEX API: not TPEX",
          "Yahoo Finance: Yahoo fundamentals 2408 HTTP 401",
          "WantGoo: WantGoo fundamentals 2408 HTTP 403"
        ],
        "source": "Yahoo Finance chart",
        "updatedAt": "2026-06-22T12:56:45.158Z"
      }
    ]
  }
}
